LICENSE
MANIFEST.in
README.md
pyproject.toml
setup.cfg
setup.py
versioneer.py
./blaze_runner/__init__.py
./blaze_runner/_version.py
./blaze_runner/blaze_runner.py
./blaze_runner/fitter.py
./blaze_runner/observation.py
./blaze_runner/versioneer.py
./blaze_runner/data/log_theme.ini
./blaze_runner/io/__init__.py
./blaze_runner/test/conftest.py
./blaze_runner/test/test_basic.py
./blaze_runner/utils/__init__.py
./blaze_runner/utils/configuration.py
./blaze_runner/utils/file_utils.py
./blaze_runner/utils/logging.py
./blaze_runner/utils/package_data.py
./docs/conf.py
blaze_runner/_version.py
blaze_runner.egg-info/PKG-INFO
blaze_runner.egg-info/SOURCES.txt
blaze_runner.egg-info/dependency_links.txt
blaze_runner.egg-info/requires.txt
blaze_runner.egg-info/top_level.txt
blaze_runner/data/log_theme.ini